class_property/__init__.py
class_property/__meta__.py
class_property/descriptors.py
class_property/__pycache__/__init__.cpython-36.pyc
class_property/__pycache__/__meta__.cpython-36.pyc
class_property/__pycache__/descriptors.cpython-36.pyc
class_property-1.0.0.dist-info/LICENSE
class_property-1.0.0.dist-info/METADATA
class_property-1.0.0.dist-info/WHEEL
class_property-1.0.0.dist-info/top_level.txt
class_property-1.0.0.dist-info/RECORD
