Metadata-Version: 2.1
Name: class-property
Version: 1.0.0
Summary: Class property that shares the same value with the class and any instance.
Home-page: https://github.com/justengel/class_property
Author: Justin Engel
Author-email: jtengel08@gmail.com
License: Proprietary
Download-URL: https://github.com/justengel/class_property/archive/v1.0.0.tar.gz
Keywords: class property class value class_property class_value classproperty classvalue
Platform: any
Classifier: Programming Language :: Python
Classifier: Programming Language :: Python :: 3
Classifier: Operating System :: OS Independent
